[
{
    "model": "booking.booking",
    "pk": 1,
    "fields": {
        "description": "",
        "agency": 2,
        "reference": "Ronny Larsen x2",
        "date_from": "2018-09-12",
        "date_to": "2018-09-22",
        "status": "PD",
        "currency": "CUC",
        "currency_factor": "1.000000",
        "cost_amount": "0.00",
        "cost_comments": null,
        "price_amount": "0.00",
        "price_comments": null,
        "invoice": null
    }
},
{
    "model": "booking.booking",
    "pk": 2,
    "fields": {
        "description": "",
        "agency": 1,
        "reference": "Peter Jensen x4",
        "date_from": "2018-09-21",
        "date_to": "2018-09-30",
        "status": "PD",
        "currency": "CUC",
        "currency_factor": "1.000000",
        "cost_amount": "0.00",
        "cost_comments": null,
        "price_amount": "0.00",
        "price_comments": null,
        "invoice": null
    }
},
{
    "model": "booking.bookingservice",
    "pk": 1,
    "fields": {
        "booking": 1,
        "name": "Booking Service",
        "description": "",
        "datetime_from": "2018-09-13T02:39:26Z",
        "datetime_to": "2018-09-23T02:39:33Z",
        "status": "PD",
        "cost_amount": "200.00",
        "cost_comments": null,
        "price_amount": "250.00",
        "price_comments": null,
        "provider": null,
        "provider_invoice": null
    }
},
{
    "model": "booking.bookingservice",
    "pk": 2,
    "fields": {
        "booking": 2,
        "name": "Booking Service",
        "description": "",
        "datetime_from": "2018-09-22T02:43:45Z",
        "datetime_to": "2018-09-24T02:43:54Z",
        "status": "PD",
        "cost_amount": "100.00",
        "cost_comments": null,
        "price_amount": "120.00",
        "price_comments": null,
        "provider": null,
        "provider_invoice": null
    }
},
{
    "model": "booking.bookingprovidedallotment",
    "pk": 1,
    "fields": {
        "service": 1,
        "room_type": 1,
        "board_type": "BB"
    }
},
{
    "model": "booking.bookingprovidedallotment",
    "pk": 2,
    "fields": {
        "service": 1,
        "room_type": 1,
        "board_type": "BB"
    }
}
]
